stepslist/__init__.py
stepslist/stepslist.py
stepslist-0.7.5.dist-info/LICENSE.md
stepslist-0.7.5.dist-info/METADATA
stepslist-0.7.5.dist-info/WHEEL
stepslist-0.7.5.dist-info/entry_points.txt
stepslist-0.7.5.dist-info/top_level.txt
stepslist-0.7.5.dist-info/RECORD
