Metadata-Version: 2.1
Name: stepslist
Version: 0.7.5
Summary: A MkDocs extension to improve the visual of ordered lists.
Home-page: https://github.com/a3bagged/stepslist-extension
Author: Chris van Liere
Author-email: c.vnliere@gmail.com
Classifier: Programming Language :: Python :: 3
Classifier: License :: OSI Approved :: MIT License
Classifier: Operating System :: OS Independent
Requires-Python: >=3.6
License-File: LICENSE.md
